{"Mean":{"confidence_interval":{"confidence_level":0.95,"lower_bound":263426.49917391303,"upper_bound":265714.2590729239},"point_estimate":264382.41977340693,"standard_error":608.3787857096688},"Median":{"confidence_interval":{"confidence_level":0.95,"lower_bound":263439.3779388084,"upper_bound":264884.1696859903},"point_estimate":263672.9365217391,"standard_error":352.7789380553767},"MedianAbsDev":{"confidence_interval":{"confidence_level":0.95,"lower_bound":82.43126931918543,"upper_bound":2004.439710935799},"point_estimate":366.9787320935092,"standard_error":522.367808015102},"Slope":{"confidence_interval":{"confidence_level":0.95,"lower_bound":263473.5518854756,"upper_bound":264141.2725885236},"point_estimate":263720.00201769243,"standard_error":172.73400701917626},"StdDev":{"confidence_interval":{"confidence_level":0.95,"lower_bound":340.59187926764423,"upper_bound":2965.9767874444055},"point_estimate":2025.3154722741765,"standard_error":769.5875938786282}}