{"Mean":{"confidence_interval":{"confidence_level":0.95,"lower_bound":626305.390261508,"upper_bound":629203.7617596939},"point_estimate":627745.9743287981,"standard_error":736.3064879157279},"Median":{"confidence_interval":{"confidence_level":0.95,"lower_bound":626473.7409523809,"upper_bound":629070.1777777778},"point_estimate":627633.8333333333,"standard_error":866.7802785931528},"MedianAbsDev":{"confidence_interval":{"confidence_level":0.95,"lower_bound":317.87119935667374,"upper_bound":4193.279983221139},"point_estimate":1921.3218975563998,"standard_error":973.3254180231336},"Slope":{"confidence_interval":{"confidence_level":0.95,"lower_bound":627361.0289322619,"upper_bound":628855.6731872879},"point_estimate":628364.854768089,"standard_error":388.16412263447097},"StdDev":{"confidence_interval":{"confidence_level":0.95,"lower_bound":1081.1866380849299,"upper_bound":3313.333584213154},"point_estimate":2455.2235197500345,"standard_error":597.8315538477202}}