{"Mean":{"confidence_interval":{"confidence_level":0.95,"lower_bound":9909589.053675737,"upper_bound":10110333.11425},"point_estimate":10016484.262165533,"standard_error":51845.11458070055},"Median":{"confidence_interval":{"confidence_level":0.95,"lower_bound":9831263.271428572,"upper_bound":10142342.833333332},"point_estimate":10122469.421428572,"standard_error":84988.15914999793},"MedianAbsDev":{"confidence_interval":{"confidence_level":0.95,"lower_bound":4067.0894277951234,"upper_bound":277051.6450146837},"point_estimate":59361.595602785885,"standard_error":80986.85942686537},"Slope":{"confidence_interval":{"confidence_level":0.95,"lower_bound":9812380.454751626,"upper_bound":10098886.110701106},"point_estimate":9935465.636734694,"standard_error":73668.10668229614},"StdDev":{"confidence_interval":{"confidence_level":0.95,"lower_bound":74900.89527070473,"upper_bound":212297.09744310006},"point_estimate":172921.720104741,"standard_error":33547.28058349693}}