{"Mean":{"confidence_interval":{"confidence_level":0.95,"lower_bound":4576.874052490903,"upper_bound":4658.467354614921},"point_estimate":4619.244456926944,"standard_error":20.9005169015},"Median":{"confidence_interval":{"confidence_level":0.95,"lower_bound":4560.932412327312,"upper_bound":4673.471430564949},"point_estimate":4636.125046579351,"standard_error":26.49867881718253},"MedianAbsDev":{"confidence_interval":{"confidence_level":0.95,"lower_bound":12.849992325244495,"upper_bound":116.95394141413632},"point_estimate":64.62664068628672,"standard_error":30.29848243414903},"Slope":{"confidence_interval":{"confidence_level":0.95,"lower_bound":4610.215142321593,"upper_bound":4652.676577816949},"point_estimate":4637.7800476019,"standard_error":10.871743984343189},"StdDev":{"confidence_interval":{"confidence_level":0.95,"lower_bound":35.260367393999665,"upper_bound":86.38446392310327},"point_estimate":69.92252073814403,"standard_error":12.572503458528953}}