{"Mean":{"confidence_interval":{"confidence_level":0.95,"lower_bound":3449.658389525144,"upper_bound":3515.2066916808026},"point_estimate":3481.8840898594854,"standard_error":16.80498452192539},"Median":{"confidence_interval":{"confidence_level":0.95,"lower_bound":3438.138209026512,"upper_bound":3515.6490670403423},"point_estimate":3487.9528775475083,"standard_error":23.89631550781},"MedianAbsDev":{"confidence_interval":{"confidence_level":0.95,"lower_bound":7.134242406899,"upper_bound":102.44565353486567},"point_estimate":43.482929548290784,"standard_error":24.037479542797225},"Slope":{"confidence_interval":{"confidence_level":0.95,"lower_bound":3471.124509099958,"upper_bound":3510.022772349867},"point_estimate":3497.1699110094123,"standard_error":10.131532007710204},"StdDev":{"confidence_interval":{"confidence_level":0.95,"lower_bound":31.271886316070002,"upper_bound":72.74810316816917},"point_estimate":55.95740883669587,"standard_error":10.879468802566812}}