{"Mean":{"confidence_interval":{"confidence_level":0.95,"lower_bound":4359.339393498093,"upper_bound":4570.127251307614},"point_estimate":4459.713561525718,"standard_error":54.111379518779266},"Median":{"confidence_interval":{"confidence_level":0.95,"lower_bound":4357.22079533592,"upper_bound":4573.602502412795},"point_estimate":4423.231000199152,"standard_error":52.7826755528178},"MedianAbsDev":{"confidence_interval":{"confidence_level":0.95,"lower_bound":32.622030357008185,"upper_bound":305.22156098249246},"point_estimate":117.93335770336033,"standard_error":69.36269406421123},"Slope":{"confidence_interval":{"confidence_level":0.95,"lower_bound":4394.329749851879,"upper_bound":4496.724244373975},"point_estimate":4448.262806791995,"standard_error":25.775544072227834},"StdDev":{"confidence_interval":{"confidence_level":0.95,"lower_bound":76.36453476381536,"upper_bound":239.5178513011003},"point_estimate":180.06189872395143,"standard_error":42.095851638365865}}