{"Mean":{"confidence_interval":{"confidence_level":0.95,"lower_bound":729183.9315480707,"upper_bound":731857.4278084077},"point_estimate":730494.3952667943,"standard_error":682.6713980662485},"Median":{"confidence_interval":{"confidence_level":0.95,"lower_bound":728644.5535714286,"upper_bound":732192.5986607142},"point_estimate":730884.2405133928,"standard_error":866.7938334598578},"MedianAbsDev":{"confidence_interval":{"confidence_level":0.95,"lower_bound":26.27858812720687,"upper_bound":4099.018277227879},"point_estimate":2798.3920617248277,"standard_error":1099.0611641526846},"Slope":{"confidence_interval":{"confidence_level":0.95,"lower_bound":730203.6614104116,"upper_bound":731944.3461834342},"point_estimate":731024.3312384045,"standard_error":432.5392184971877},"StdDev":{"confidence_interval":{"confidence_level":0.95,"lower_bound":1287.7099589385869,"upper_bound":2866.2674500108124},"point_estimate":2278.9941707895055,"standard_error":408.00503811357237}}