{"Mean":{"confidence_interval":{"confidence_level":0.95,"lower_bound":6104.539269318092,"upper_bound":6646.351213426913},"point_estimate":6389.59523464029,"standard_error":138.52680817381548},"Median":{"confidence_interval":{"confidence_level":0.95,"lower_bound":6011.534618573798,"upper_bound":6746.207810155571},"point_estimate":6489.6482587064675,"standard_error":190.30429043534974},"MedianAbsDev":{"confidence_interval":{"confidence_level":0.95,"lower_bound":73.74714735988084,"upper_bound":742.8369655692627},"point_estimate":406.08364361043346,"standard_error":180.98606922662935},"Slope":{"confidence_interval":{"confidence_level":0.95,"lower_bound":6462.08684834619,"upper_bound":6813.787817004134},"point_estimate":6696.065156899485,"standard_error":89.68542802967009},"StdDev":{"confidence_interval":{"confidence_level":0.95,"lower_bound":202.1553040742094,"upper_bound":564.1475965302183},"point_estimate":461.006141523557,"standard_error":86.1233214247696}}