{"Mean":{"confidence_interval":{"confidence_level":0.95,"lower_bound":129482.01573561346,"upper_bound":131277.6955546766},"point_estimate":130337.24736660463,"standard_error":459.56272826727366},"Median":{"confidence_interval":{"confidence_level":0.95,"lower_bound":129289.67508143323,"upper_bound":131358.0325732899},"point_estimate":130139.8384907709,"standard_error":584.525086732047},"MedianAbsDev":{"confidence_interval":{"confidence_level":0.95,"lower_bound":169.9223766575332,"upper_bound":2609.542220120873},"point_estimate":1327.2824945793434,"standard_error":577.771458259761},"Slope":{"confidence_interval":{"confidence_level":0.95,"lower_bound":130269.82995446221,"upper_bound":132441.64205863484},"point_estimate":131463.4443800499,"standard_error":579.866216792238},"StdDev":{"confidence_interval":{"confidence_level":0.95,"lower_bound":762.5588544619958,"upper_bound":2051.2231468645837},"point_estimate":1533.330496216323,"standard_error":342.92066662708635}}