{"Mean":{"confidence_interval":{"confidence_level":0.95,"lower_bound":78763.54531299787,"upper_bound":86168.43719183336},"point_estimate":82610.67201284398,"standard_error":1899.0164818011233},"Median":{"confidence_interval":{"confidence_level":0.95,"lower_bound":76351.28066914498,"upper_bound":87844.56725526642},"point_estimate":85202.6984953089,"standard_error":3557.6677973839996},"MedianAbsDev":{"confidence_interval":{"confidence_level":0.95,"lower_bound":363.70724465815147,"upper_bound":10241.112871827032},"point_estimate":5313.92779919466,"standard_error":2940.504726158105},"Slope":{"confidence_interval":{"confidence_level":0.95,"lower_bound":84277.34953512109,"upper_bound":88106.5376978412},"point_estimate":86957.84971756868,"standard_error":999.9334360181088},"StdDev":{"confidence_interval":{"confidence_level":0.95,"lower_bound":3683.8006142007503,"upper_bound":7352.231713926461},"point_estimate":6329.6159535480565,"standard_error":926.4383610587291}}