{"Mean":{"confidence_interval":{"confidence_level":0.95,"lower_bound":538323.7211676955,"upper_bound":565180.6625771604},"point_estimate":551347.6051286007,"standard_error":6908.460091777656},"Median":{"confidence_interval":{"confidence_level":0.95,"lower_bound":527856.5925925926,"upper_bound":572696.2268518518},"point_estimate":547563.620164609,"standard_error":10075.52621489226},"MedianAbsDev":{"confidence_interval":{"confidence_level":0.95,"lower_bound":2646.0977585779615,"upper_bound":37714.87538104437},"point_estimate":30540.687438843815,"standard_error":9549.043391286204},"Slope":{"confidence_interval":{"confidence_level":0.95,"lower_bound":532038.9449545965,"upper_bound":554043.0389545616},"point_estimate":541460.0358826359,"standard_error":5699.7322816705855},"StdDev":{"confidence_interval":{"confidence_level":0.95,"lower_bound":12609.048702894948,"upper_bound":28303.098378221483},"point_estimate":23104.977367424293,"standard_error":3886.827151789453}}