{"Mean":{"confidence_interval":{"confidence_level":0.95,"lower_bound":844628.2128950242,"upper_bound":852200.7145962785},"point_estimate":848421.3206984898,"standard_error":1937.1724036278968},"Median":{"confidence_interval":{"confidence_level":0.95,"lower_bound":841518.3422330098,"upper_bound":854951.7421790722},"point_estimate":850051.9277912622,"standard_error":3669.7672739715726},"MedianAbsDev":{"confidence_interval":{"confidence_level":0.95,"lower_bound":975.1675377843718,"upper_bound":10127.626565805456},"point_estimate":9110.562264153248,"standard_error":2710.71687835169},"Slope":{"confidence_interval":{"confidence_level":0.95,"lower_bound":843840.6960023774,"upper_bound":853776.6502773925},"point_estimate":849100.0868490733,"standard_error":2700.4726637601198},"StdDev":{"confidence_interval":{"confidence_level":0.95,"lower_bound":4305.3543262952835,"upper_bound":7433.8322853628415},"point_estimate":6464.4265157291575,"standard_error":815.964042041264}}