{"Mean":{"confidence_interval":{"confidence_level":0.95,"lower_bound":5111.874773652654,"upper_bound":5195.192562022125},"point_estimate":5157.9879689569825,"standard_error":21.444064472696645},"Median":{"confidence_interval":{"confidence_level":0.95,"lower_bound":5133.873657881893,"upper_bound":5205.791410444119},"point_estimate":5169.163491482488,"standard_error":17.85478048086063},"MedianAbsDev":{"confidence_interval":{"confidence_level":0.95,"lower_bound":2.68323581863962,"upper_bound":98.88214634112344},"point_estimate":45.178515336891216,"standard_error":22.932315059091817},"Slope":{"confidence_interval":{"confidence_level":0.95,"lower_bound":5149.2286285051605,"upper_bound":5214.698327551468},"point_estimate":5186.315985624917,"standard_error":17.139430952735886},"StdDev":{"confidence_interval":{"confidence_level":0.95,"lower_bound":25.463245248194955,"upper_bound":100.6594995999661},"point_estimate":71.5393923196648,"standard_error":21.600832364580086}}