{"Mean":{"confidence_interval":{"confidence_level":0.95,"lower_bound":67757.26039479635,"upper_bound":68988.8326115691},"point_estimate":68344.21023939963,"standard_error":316.86485136255106},"Median":{"confidence_interval":{"confidence_level":0.95,"lower_bound":67425.4655118439,"upper_bound":68933.17031896762},"point_estimate":68331.67276600926,"standard_error":506.19263877724103},"MedianAbsDev":{"confidence_interval":{"confidence_level":0.95,"lower_bound":111.00782293791967,"upper_bound":2054.5110724586643},"point_estimate":1022.5827200851195,"standard_error":464.86871314853},"Slope":{"confidence_interval":{"confidence_level":0.95,"lower_bound":67380.81890621527,"upper_bound":68608.52319369899},"point_estimate":67938.893534953,"standard_error":330.78944214019367},"StdDev":{"confidence_interval":{"confidence_level":0.95,"lower_bound":599.8867066616186,"upper_bound":1376.1157646918616},"point_estimate":1054.835468598015,"standard_error":218.11343398747385}}