{"Mean":{"confidence_interval":{"confidence_level":0.95,"lower_bound":9788.739869920943,"upper_bound":10101.594752766616},"point_estimate":9947.449623070594,"standard_error":80.39951022234688},"Median":{"confidence_interval":{"confidence_level":0.95,"lower_bound":9676.067015995588,"upper_bound":10192.62248345284},"point_estimate":9982.741882699025,"standard_error":128.7047568145771},"MedianAbsDev":{"confidence_interval":{"confidence_level":0.95,"lower_bound":80.017988199502,"upper_bound":451.4584583862332},"point_estimate":343.6927746591738,"standard_error":98.70564577130568},"Slope":{"confidence_interval":{"confidence_level":0.95,"lower_bound":9995.05193690908,"upper_bound":10227.176767328552},"point_estimate":10150.267177527381,"standard_error":59.32080546471119},"StdDev":{"confidence_interval":{"confidence_level":0.95,"lower_bound":161.4468570670799,"upper_bound":317.1045015342467},"point_estimate":266.90634059630776,"standard_error":39.14038210867305}}